evilredirex/__init__.py
evilredirex/main.py
evilredirex-1.2.dist-info/METADATA
evilredirex-1.2.dist-info/WHEEL
evilredirex-1.2.dist-info/entry_points.txt
evilredirex-1.2.dist-info/top_level.txt
evilredirex-1.2.dist-info/RECORD
