Metadata-Version: 2.1
Name: evilredirex
Version: 1.2
Summary: A tool to test for open redirects and XSS vulnerabilities.
Home-page: https://github.com/Evil-twinz/Evil-redirex
Author: SrilakiVarma
Author-email: srilakivarma@gmail.com
Classifier: Programming Language :: Python :: 3
Classifier: License :: OSI Approved :: MIT License
Classifier: Operating System :: OS Independent
Requires-Python: >=3.6
Requires-Dist: requests
Requires-Dist: selenium
Requires-Dist: termcolor
Requires-Dist: urllib3
